setup.cfg
setup.py
bulk_geocoding/__init__.py
bulk_geocoding/bulk_geocoding.py
bulk_geocoding/test_bulk_geocoding.py
bulk_geocoding/utils.py
bulk_geocoding.egg-info/PKG-INFO
bulk_geocoding.egg-info/SOURCES.txt
bulk_geocoding.egg-info/dependency_links.txt
bulk_geocoding.egg-info/requires.txt
bulk_geocoding.egg-info/top_level.txt