Metadata-Version: 1.2
Name: bulk-geocoding
Version: 0.1.1
Summary: Python client for geocoding adresses in bulk using adresse.data.gouv.fr API
Home-page: https://github.com/MTES-MCT/bulk-geocoding-python-client
Author: Benoît Guigal
Author-email: benoit.guigal@protonmail.com
License: UNKNOWN
Download-URL: https://github.com/MTES-MCT/bulk-geocoding-python-client/archive/v0.1.1.tar.gz
Platform: UNKNOWN
Requires-Python: >=3.6
